README.md
setup.py
hopkins_ep_timesheet_utils.egg-info/PKG-INFO
hopkins_ep_timesheet_utils.egg-info/SOURCES.txt
hopkins_ep_timesheet_utils.egg-info/dependency_links.txt
hopkins_ep_timesheet_utils.egg-info/top_level.txt
shared_utils/__init__.py
shared_utils/schema_utils.py